Workbook

Sheet Dashboard
A1: CHALLENGE ACCOUNT SCOREBOARD
A2: Aspiration: $1,000,000 | Structure: ride hard below $100k, bank 25% at every double after
A4: Account value (positions + cash) | B4: =Positions!E29 -> 6000.004 | C4: Live from Positions tab
A5: Banked floors (locked forever) | B5: =Milestones!E13 -> 0 | C5: From Milestones tab — never goes back on the table
A6: Tax reserved to date | B6: =SUMIFS('Tax Reserve'!F5:F10,'Tax Reserve'!G5:G10,"Y") -> 0 | C6: Quarterly 30% skims actually moved
A7: TOTAL SCORE (account + banked + reserved) | B7: =B4+B5+B6 -> 6000.004 | C7: This is the number that measures success
A9: Next milestone | B9: =IF(Positions!E29<100000,100000,IF(Positions!E29<200000,200000,IF(Positions!E29<400000,400000,IF(Positions!E29<800000,800000,1000000)))) -> 100000 | C9: Bank 25% when you cross it
A10: Distance to next milestone | B10: =B9-Positions!E29 -> 93999.996
A11: Progress to $1M aspiration | B11: =B7/1000000 -> 0.006000004 | C11: Direction, not a verdict
A13: Net realized gains this tax year | B13: ='Trade Log'!G48 -> 1455.11 | C13: Drives the quarterly tax skim
A14: Lead vs VOO shadow | B14: =Benchmark!B26 -> 0.004 | C14: The honest test — positive after 12 months = real edge
A15: Parked pile total (context only — NOT in score) | B15: ='Parked Pile'!H19 -> 22597.25 | C15: The foundation. Funding source and skim destination — never refill fuel
A16: Net contributed to challenge account | B16: ='Cash Flow'!B69 -> 6000 | C16: True stake so far — from the Cash Flow ledger
A17: HOW TO USE
A18: 1. Positions tab: enter each buy (blue cells). Update Current Price column to refresh the score.
A19: 2. Trade Log: log every close. The YTD realized number feeds the tax skim.
A20: 3. Tax Reserve: once a quarter, enter YTD realized gains, move 30% out of play, mark Y.
A21: 4. Milestones: when the Dashboard shows a milestone hit, bank 25% into VOO, record it. Status column will tell you.
A22: 5. Benchmark: every time you deposit money, add a row with that day's VOO price. Check the lead monthly.
A23: 6. Rules tab: read it after every big win and every big loss. Especially the wins.
A24: LEGEND: Blue text = you type it. Black = formula, leave alone. Green = pulls from another tab. Yellow fill = key inputs.

Sheet Rules
B1: CHALLENGE ACCOUNT — THE RULES
B2: Written while calm. The person who wrote these is smarter about risk than the person staring at a big number later.
B4: THE GOAL
B5: Compound aggressively, lock in floors as you climb, and let the final height be the prize. $1M is the aspiration, not a pass/fail line. Every banked dollar is a retirement upgrade already purchased.
B7: MONEY MANAGEMENT
B8: 1. Below $100,000: everything rides. Full aggression, no skims except the tax reserve.
B9: 2. At $100,000 and at every double after (200k, 400k, 800k): bank 25% of the account into VOO in the parked pile. Banked money NEVER returns to the table.
B10: 3. Tax reserve: every quarter, move 30% of net realized gains YTD out of play. This rule is non-negotiable. It is what makes a blown account a shrug instead of a debt.
B11: 4. The bankroll is never refilled from the parked pile (NVDA, TSLA, MU, AMAT, and the other winners). New money comes only from scheduled long-term trims or fresh income.
B12: 5. Stake additions: only from long-term trims (held >1 year) to avoid short-term tax rates.
B14: TRADING GUARDRAILS (the Xu rules)
B15: 6. No margin. No options. No chasing stocks that have already run.
... B21: 10. Success = banked pile + account value when done. Ending at $180k means winning $180k, not missing 82% of a million.

Sheet Cash Flow
A1: CASH LEDGER — every dollar in, out, and deployed
A2: Log each event. Types that ADD cash: Deposit, Sell, Dividend. Types that REMOVE cash: Buy, Withdrawal, Tax Skim, Milestone Bank, Fee. Amount is always positive — the Type decides the direction.
A4: Date | B4: Type | C4: Amount | D4: Ticker | E4: Source / Destination | F4: Notes | G4: Running Cash
A5: 46244 | B5: Deposit | C5: 6000 | E5: Cash App sales | F5: EXAMPLE — initial funding from loser/dead-weight sales | G5: =IF(B5="","",IF(OR(B5="Deposit",B5="Sell",B5="Dividend"),C5,-C5)) -> 6000
A6: 46246 | B6: Buy | C6: 6004.68 | D6: NBIS | F6: EXAMPLE — matches Positions example row | G6: =IF(B6="","",N(G5)+IF(OR(B6="Deposit",B6="Sell",B6="Dividend"),C6,-C6)) -> -4.68
G7: =IF(B7="","",N(G6)+IF(OR(B7="Deposit",B7="Sell",B7="Dividend"),C7,-C7))
G8: =IF(B8="","",N(G7)+IF(OR(B8="Deposit",B8="Sell",B8="Dividend"),C8,-C8))
G9: =IF(B9="","",N(G8)+IF(OR(B9="Deposit",B9="Sell",B9="Dividend"),C9,-C9))
G10: =IF(B10="","",N(G9)+IF(OR(B10="Deposit",B10="Sell",B10="Dividend"),C10,-C10))
G11: =IF(B11="","",N(G10)+IF(OR(B11="Deposit",B11="Sell",B11="Dividend"),C11,-C11))
G12: =IF(B12="","",N(G11)+IF(OR(B12="Deposit",B12="Sell",B12="Dividend"),C12,-C12))
G13: =IF(B13="","",N(G12)+IF(OR(B13="Deposit",B13="Sell",B13="Dividend"),C13,-C13))
G14: =IF(B14="","",N(G13)+IF(OR(B14="Deposit",B14="Sell",B14="Dividend"),C14,-C14))
G15: =IF(B15="","",N(G14)+IF(OR(B15="Deposit",B15="Sell",B15="Dividend"),C15,-C15))
G16: =IF(B16="","",N(G15)+IF(OR(B16="Deposit",B16="Sell",B16="Dividend"),C16,-C16))
G17: =IF(B17="","",N(G16)+IF(OR(B17="Deposit",B17="Sell",B17="Dividend"),C17,-C17))
G18: =IF(B18="","",N(G17)+IF(OR(B18="Deposit",B18="Sell",B18="Dividend"),C18,-C18))
... G64: =IF(B64="","",N(G63)+IF(OR(B64="Deposit",B64="Sell",B64="Dividend"),C64,-C64))
A66: SUMMARY
A67: Total deposits | B67: =SUMIFS($C$5:$C$64,$B$5:$B$64,"Deposit") -> 6000
A68: Total withdrawals | B68: =SUMIFS($C$5:$C$64,$B$5:$B$64,"Withdrawal") -> 0
A69: NET CONTRIBUTED (deposits - withdrawals) | B69: =B67-B68 -> 6000
A70: Total buys | B70: =SUMIFS($C$5:$C$64,$B$5:$B$64,"Buy") -> 6004.68
A71: Total sells | B71: =SUMIFS($C$5:$C$64,$B$5:$B$64,"Sell") -> 0
A72: Dividends received | B72: =SUMIFS($C$5:$C$64,$B$5:$B$64,"Dividend") -> 0
A73: Tax skims moved out | B73: =SUMIFS($C$5:$C$64,$B$5:$B$64,"Tax Skim") -> 0
A74: Milestone banks moved out | B74: =SUMIFS($C$5:$C$64,$B$5:$B$64,"Milestone Bank") -> 0
A75: Fees paid | B75: =SUMIFS($C$5:$C$64,$B$5:$B$64,"Fee") -> 0
A76: CURRENT CASH BALANCE | B76: =B67-B68-B70+B71+B72-B73-B74-B75 -> -4.68
A78: Funding-phase check: NET CONTRIBUTED is your true stake. Every Deposit row here should also get a row on the Benchmark tab with that day's VOO price, so the shadow stays honest.

Sheet Positions
A1: OPEN POSITIONS — Challenge Account
A2: Blue cells are yours to edit. Update Current Price whenever you check the score. Delete the example row when you make your first trade.
A4: Ticker | B4: Buy Date | C4: Shares | D4: Avg Cost | E4: Cost Basis | F4: Current Price | G4: Market Value | H4: Unrealized $ | I4: Unrealized % | J4: Days Held | K4: Long-Term On | L4: Exit Target $ | M4: Bail Point $ | N4: Thesis / Catalyst
A5: NBIS | B5: 46244 | C5: 26.6 | D5: 225.74 | E5: =C5*D5 -> 6004.684 | F5: 225.74 | G5: =C5*F5 -> 6004.684 | H5: =G5-E5 -> 0 | I5: =IF(E5=0,0,H5/E5) -> 0 | J5: =IF(B5="","",TODAY()-B5) -> -6 | K5: =IF(B5="","",B5+366) -> 46610 | L5: 290 | M5: 190 | N5: EXAMPLE ROW — replace with your first pick. AI infra momentum, target +28%.
E6: =IF(C6="","",C6*D6) | G6: =IF(C6="","",C6*F6) | H6: =IF(C6="","",G6-E6) | I6: =IF(OR(C6="",E6=0),"",H6/E6) | J6: =IF(B6="","",TODAY()-B6) | K6: =IF(B6="","",B6+366)
E7: =IF(C7="","",C7*D7) | G7: =IF(C7="","",C7*F7) | H7: =IF(C7="","",G7-E7) | I7: =IF(OR(C7="",E7=0),"",H7/E7) | J7: =IF(B7="","",TODAY()-B7) | K7: =IF(B7="","",B7+366)
E8: =IF(C8="","",C8*D8) | G8: =IF(C8="","",C8*F8) | H8: =IF(C8="","",G8-E8) | I8: =IF(OR(C8="",E8=0),"",H8/E8) | J8: =IF(B8="","",TODAY()-B8) | K8: =IF(B8="","",B8+366)
E9: =IF(C9="","",C9*D9) | G9: =IF(C9="","",C9*F9) | H9: =IF(C9="","",G9-E9) | I9: =IF(OR(C9="",E9=0),"",H9/E9) | J9: =IF(B9="","",TODAY()-B9) | K9: =IF(B9="","",B9+366)
E10: =IF(C10="","",C10*D10) | G10: =IF(C10="","",C10*F10) | H10: =IF(C10="","",G10-E10) | I10: =IF(OR(C10="",E10=0),"",H10/E10) | J10: =IF(B10="","",TODAY()-B10) | K10: =IF(B10="","",B10+366)
E11: =IF(C11="","",C11*D11) | G11: =IF(C11="","",C11*F11) | H11: =IF(C11="","",G11-E11) | I11: =IF(OR(C11="",E11=0),"",H11/E11) | J11: =IF(B11="","",TODAY()-B11) | K11: =IF(B11="","",B11+366)
E12: =IF(C12="","",C12*D12) | G12: =IF(C12="","",C12*F12) | H12: =IF(C12="","",G12-E12) | I12: =IF(OR(C12="",E12=0),"",H12/E12) | J12: =IF(B12="","",TODAY()-B12) | K12: =IF(B12="","",B12+366)
E13: =IF(C13="","",C13*D13) | G13: =IF(C13="","",C13*F13) | H13: =IF(C13="","",G13-E13) | I13: =IF(OR(C13="",E13=0),"",H13/E13) | J13: =IF(B13="","",TODAY()-B13) | K13: =IF(B13="","",B13+366)
E14: =IF(C14="","",C14*D14) | G14: =IF(C14="","",C14*F14) | H14: =IF(C14="","",G14-E14) | I14: =IF(OR(C14="",E14=0),"",H14/E14) | J14: =IF(B14="","",TODAY()-B14) | K14: =IF(B14="","",B14+366)
E15: =IF(C15="","",C15*D15) | G15: =IF(C15="","",C15*F15) | H15: =IF(C15="","",G15-E15) | I15: =IF(OR(C15="",E15=0),"",H15/E15) | J15: =IF(B15="","",TODAY()-B15) | K15: =IF(B15="","",B15+366)
E16: =IF(C16="","",C16*D16) | G16: =IF(C16="","",C16*F16) | H16: =IF(C16="","",G16-E16) | I16: =IF(OR(C16="",E16=0),"",H16/E16) | J16: =IF(B16="","",TODAY()-B16) | K16: =IF(B16="","",B16+366)
E17: =IF(C17="","",C17*D17) | G17: =IF(C17="","",C17*F17) | H17: =IF(C17="","",G17-E17) | I17: =IF(OR(C17="",E17=0),"",H17/E17) | J17: =IF(B17="","",TODAY()-B17) | K17: =IF(B17="","",B17+366)
... E24: =IF(C24="","",C24*D24) | G24: =IF(C24="","",C24*F24) | H24: =IF(C24="","",G24-E24) | I24: =IF(OR(C24="",E24=0),"",H24/E24) | J24: =IF(B24="","",TODAY()-B24) | K24: =IF(B24="","",B24+366)
A26: TOTAL INVESTED | E26: =SUM(E5:E24) -> 6004.684 | G26: =SUM(G5:G24) -> 6004.684 | H26: =SUM(H5:H24) -> 0 | I26: =IF(E26=0,0,H26/E26) -> 0
A28: Cash in account (auto from Cash Flow tab) | E28: ='Cash Flow'!B76 -> -4.68
A29: ACCOUNT TOTAL (positions + cash) | E29: =G26+E28 -> 6000.004

Sheet Trade Log
A1: CLOSED TRADES
A2: Log every close. ST = held 365 days or less (taxed ~28-30%). LT = held over a year (~21%). Flag wash sales so you don't count disallowed losses.
A4: Ticker | B4: Open Date | C4: Close Date | D4: Days Held | E4: Cost Basis | F4: Proceeds | G4: Realized Gain $ | H4: Realized % | I4: ST / LT | J4: Tax Year | K4: Wash Sale? (Y/N) | L4: Notes
A5: MU | B5: 46083 | C5: 46188 | D5: =IF(OR(B5="",C5=""),"",C5-B5) -> 105 | E5: 1000 | F5: 2455.11 | G5: =F5-E5 -> 1455.11 | H5: =IF(E5=0,"",G5/E5) -> 1.45511 | I5: =IF(D5="","",IF(D5>365,"LT","ST")) -> ST | J5: =IF(C5="","",YEAR(C5)) -> 2026 | K5: N | L5: EXAMPLE ROW (your realized MU gain lives in Cash App, not here) — replace.
D6: =IF(OR(B6="",C6=""),"",C6-B6) | G6: =IF(OR(E6="",F6=""),"",F6-E6) | H6: =IF(OR(E6="",E6=0),"",G6/E6) | I6: =IF(D6="","",IF(D6>365,"LT","ST")) | J6: =IF(C6="","",YEAR(C6))
D7: =IF(OR(B7="",C7=""),"",C7-B7) | G7: =IF(OR(E7="",F7=""),"",F7-E7) | H7: =IF(OR(E7="",E7=0),"",G7/E7) | I7: =IF(D7="","",IF(D7>365,"LT","ST")) | J7: =IF(C7="","",YEAR(C7))
D8: =IF(OR(B8="",C8=""),"",C8-B8) | G8: =IF(OR(E8="",F8=""),"",F8-E8) | H8: =IF(OR(E8="",E8=0),"",G8/E8) | I8: =IF(D8="","",IF(D8>365,"LT","ST")) | J8: =IF(C8="","",YEAR(C8))
D9: =IF(OR(B9="",C9=""),"",C9-B9) | G9: =IF(OR(E9="",F9=""),"",F9-E9) | H9: =IF(OR(E9="",E9=0),"",G9/E9) | I9: =IF(D9="","",IF(D9>365,"LT","ST")) | J9: =IF(C9="","",YEAR(C9))
D10: =IF(OR(B10="",C10=""),"",C10-B10) | G10: =IF(OR(E10="",F10=""),"",F10-E10) | H10: =IF(OR(E10="",E10=0),"",G10/E10) | I10: =IF(D10="","",IF(D10>365,"LT","ST")) | J10: =IF(C10="","",YEAR(C10))
D11: =IF(OR(B11="",C11=""),"",C11-B11) | G11: =IF(OR(E11="",F11=""),"",F11-E11) | H11: =IF(OR(E11="",E11=0),"",G11/E11) | I11: =IF(D11="","",IF(D11>365,"LT","ST")) | J11: =IF(C11="","",YEAR(C11))
D12: =IF(OR(B12="",C12=""),"",C12-B12) | G12: =IF(OR(E12="",F12=""),"",F12-E12) | H12: =IF(OR(E12="",E12=0),"",G12/E12) | I12: =IF(D12="","",IF(D12>365,"LT","ST")) | J12: =IF(C12="","",YEAR(C12))
D13: =IF(OR(B13="",C13=""),"",C13-B13) | G13: =IF(OR(E13="",F13=""),"",F13-E13) | H13: =IF(OR(E13="",E13=0),"",G13/E13) | I13: =IF(D13="","",IF(D13>365,"LT","ST")) | J13: =IF(C13="","",YEAR(C13))
D14: =IF(OR(B14="",C14=""),"",C14-B14) | G14: =IF(OR(E14="",F14=""),"",F14-E14) | H14: =IF(OR(E14="",E14=0),"",G14/E14) | I14: =IF(D14="","",IF(D14>365,"LT","ST")) | J14: =IF(C14="","",YEAR(C14))
D15: =IF(OR(B15="",C15=""),"",C15-B15) | G15: =IF(OR(E15="",F15=""),"",F15-E15) | H15: =IF(OR(E15="",E15=0),"",G15/E15) | I15: =IF(D15="","",IF(D15>365,"LT","ST")) | J15: =IF(C15="","",YEAR(C15))
D16: =IF(OR(B16="",C16=""),"",C16-B16) | G16: =IF(OR(E16="",F16=""),"",F16-E16) | H16: =IF(OR(E16="",E16=0),"",G16/E16) | I16: =IF(D16="","",IF(D16>365,"LT","ST")) | J16: =IF(C16="","",YEAR(C16))
D17: =IF(OR(B17="",C17=""),"",C17-B17) | G17: =IF(OR(E17="",F17=""),"",F17-E17) | H17: =IF(OR(E17="",E17=0),"",G17/E17) | I17: =IF(D17="","",IF(D17>365,"LT","ST")) | J17: =IF(C17="","",YEAR(C17))
... D45: =IF(OR(B45="",C45=""),"",C45-B45) | G45: =IF(OR(E45="",F45=""),"",F45-E45) | H45: =IF(OR(E45="",E45=0),"",G45/E45) | I45: =IF(D45="","",IF(D45>365,"LT","ST")) | J45: =IF(C45="","",YEAR(C45))
A48: Net realized — current tax year: | G48: =SUMIFS(G5:G45,J5:J45,YEAR(TODAY()),K5:K45,"N") -> 1455.11 | H48: (excludes wash-sale-flagged losses)

Sheet Milestones
A1: MILESTONES & BANKED FLOORS
A2: Below $100k everything rides. At each milestone, bank 25% of the account value into VOO in the parked pile. Banked money never returns.
A4: Milestone | B4: Account Value at Hit | C4: Skim (25%) | D4: Date Hit | E4: Actually Banked $ | F4: Where Parked | G4: Cumulative Floor | H4: Status
A5: 100000 | C5: =IF(B5="","",B5*0.25) | G5: =SUM($E$5:E5) -> 0 | H5: =IF(E5<>"","BANKED",IF(Positions!$E$29>=A5,"HIT — BANK NOW","not yet")) -> not yet
A6: 200000 | C6: =IF(B6="","",B6*0.25) | G6: =SUM($E$5:E6) -> 0 | H6: =IF(E6<>"","BANKED",IF(Positions!$E$29>=A6,"HIT — BANK NOW","not yet")) -> not yet
A7: 400000 | C7: =IF(B7="","",B7*0.25) | G7: =SUM($E$5:E7) -> 0 | H7: =IF(E7<>"","BANKED",IF(Positions!$E$29>=A7,"HIT — BANK NOW","not yet")) -> not yet
A8: 800000 | C8: =IF(B8="","",B8*0.25) | G8: =SUM($E$5:E8) -> 0 | H8: =IF(E8<>"","BANKED",IF(Positions!$E$29>=A8,"HIT — BANK NOW","not yet")) -> not yet
A9: 1000000 | C9: =IF(B9="","",B9*0.25) | G9: =SUM($E$5:E9) -> 0 | H9: =IF(E9<>"","BANKED",IF(Positions!$E$29>=A9,"HIT — BANK NOW","not yet")) -> not yet
A11: Note: $1M row is the aspiration marker. If the account doubles past $800k, keep adding rows (1.6M...) with the same 25% rule.
A13: TOTAL BANKED (the floor) | E13: =SUM(E5:E9) -> 0

Sheet Tax Reserve
A1: QUARTERLY TAX SKIM — 30% of net realized gains
A2: The rule that prevents the 2018 Kevin Xu problem: owing tax on gains that later losses already vaporized. Check quarterly. If net realized YTD is negative, nothing to reserve.
A4: Quarter | B4: Check Date | C4: Net Realized Gain YTD | D4: Reserve Target (30%) | E4: Already Reserved | F4: Move Out Now | G4: Moved? (Y/N)
A5: Q3 2026 | D5: =IF(C5="","",MAX(0,C5*0.3)) | E5: 0 | F5: =IF(D5="","",MAX(0,D5-E5))
A6: Q4 2026 | D6: =IF(C6="","",MAX(0,C6*0.3)) | E6: =IF(ROW()=5,0,SUMIFS($F$5:F5,$G$5:G5,"Y")) -> 0 | F6: =IF(D6="","",MAX(0,D6-E6))
A7: Q1 2027 | D7: =IF(C7="","",MAX(0,C7*0.3)) | E7: =IF(ROW()=5,0,SUMIFS($F$5:F6,$G$5:G6,"Y")) -> 0 | F7: =IF(D7="","",MAX(0,D7-E7))
A8: Q2 2027 | D8: =IF(C8="","",MAX(0,C8*0.3)) | E8: =IF(ROW()=5,0,SUMIFS($F$5:F7,$G$5:G7,"Y")) -> 0 | F8: =IF(D8="","",MAX(0,D8-E8))
A9: Q3 2027 | D9: =IF(C9="","",MAX(0,C9*0.3)) | E9: =IF(ROW()=5,0,SUMIFS($F$5:F8,$G$5:G8,"Y")) -> 0 | F9: =IF(D9="","",MAX(0,D9-E9))
A10: Q4 2027 | D10: =IF(C10="","",MAX(0,C10*0.3)) | E10: =IF(ROW()=5,0,SUMIFS($F$5:F9,$G$5:G9,"Y")) -> 0 | F10: =IF(D10="","",MAX(0,D10-E10))
A12: Tip: Column C for the challenge account = 'Net realized — current tax year' on the Trade Log tab. Enter it manually so cross-year rollovers stay under your control.

Sheet Benchmark
A1: SCOREBOARD vs VOO — the honest test
A2: Every deposit gets a shadow: what if that same money had bought VOO that day? Beat the shadow after tax for 12 months and the edge is real.
A4: DEPOSITS & SHADOW VOO PURCHASES
A5: Deposit Date | B5: Amount In | C5: VOO Price That Day | D5: Shadow VOO Shares
A6: 46244 | B6: 6000 | C6: 620 | D6: =IF(OR(B6="",C6="",C6=0),"",B6/C6) -> 9.6774194 | E6: EXAMPLE ROW — set real date, amount, and that day's VOO price.
D7: =IF(OR(B7="",C7="",C7=0),"",B7/C7)
D8: =IF(OR(B8="",C8="",C8=0),"",B8/C8)
D9: =IF(OR(B9="",C9="",C9=0),"",B9/C9)
D10: =IF(OR(B10="",C10="",C10=0),"",B10/C10)
D11: =IF(OR(B11="",C11="",C11=0),"",B11/C11)
D12: =IF(OR(B12="",C12="",C12=0),"",B12/C12)
D13: =IF(OR(B13="",C13="",C13=0),"",B13/C13)
D14: =IF(OR(B14="",C14="",C14=0),"",B14/C14)
D15: =IF(OR(B15="",C15="",C15=0),"",B15/C15)
D16: =IF(OR(B16="",C16="",C16=0),"",B16/C16)
D17: =IF(OR(B17="",C17="",C17=0),"",B17/C17)
D18: =IF(OR(B18="",C18="",C18=0),"",B18/C18)
A21: SCORE CHECK
A22: VOO price today | B22: 620
A23: Total deposited | B23: =SUM(B6:B18) -> 6000
A24: Shadow VOO value today | B24: =SUM(D6:D18)*B22 -> 6000
A25: Your side: account + banked floors + tax reserved | B25: =Positions!E29+Milestones!E13+SUMIFS('Tax Reserve'!F5:F10,'Tax Reserve'!G5:G10,"Y") -> 6000.004
A26: LEAD vs VOO | B26: =B25-B24 -> 0.004
A27: Lead % | B27: =IF(B24=0,"",B26/B24) -> 6.6666667e-07
A29: Note: this compares pre-tax account value to a buy-and-hold VOO shadow. Your real hurdle is higher: short-term trades pay ~28-30% on gains while VOO held long-term pays ~21% only when sold. If the lead is thin, VOO is winning after tax.

Sheet Parked Pile
A1: PARKED PILE — the foundation. NOT part of the challenge score.
A2: Fill in Buy Date (blue) for each position — oldest lot if you bought in pieces. LT Status flips to FUNDING UNLOCKED when a trim gets long-term tax rates (~21% vs ~28-30%).
A4: Ticker | B4: Account | C4: Category | D4: Shares | E4: Avg Cost | F4: Cost Basis | G4: Current Price | H4: Market Value | I4: Unrealized $ | J4: Unrealized % | K4: Buy Date | L4: Long-Term On | M4: LT Status | N4: Trim Rank | O4: Notes
A5: MU | B5: Cash App | C5: Semi/AI | D5: 5.5587348 | E5: 262.07 | F5: =IF(OR(D5="",E5=""),"",D5*E5) -> 1456.7776 | G5: 892.67 | H5: =IF(OR(D5="",G5=""),"",D5*G5) -> 4962.1157 | I5: =IF(OR(F5="",H5=""),"",H5-F5) -> 3505.3381 | J5: =IF(OR(F5="",F5=0,I5=""),"",I5/F5) -> 2.4062273 | L5: =IF(K5="","",K5+366) | M5: =IF(K5="","enter buy date",IF(TODAY()>=L5,"FUNDING UNLOCKED",L5-TODAY()&" days to go")) -> enter buy date | O5: Biggest gain, biggest position — trim first
A6: AMAT | B6: Cash App | C6: Semi/AI | D6: 4.3909583 | E6: 228.66 | F6: =IF(OR(D6="",E6=""),"",D6*E6) -> 1004.0365 | G6: 546.62 | H6: =IF(OR(D6="",G6=""),"",D6*G6) -> 2400.1856 | I6: =IF(OR(F6="",H6=""),"",H6-F6) -> 1396.1491 | J6: =IF(OR(F6="",F6=0,I6=""),"",I6/F6) -> 1.3905362 | L6: =IF(K6="","",K6+366) | M6: =IF(K6="","enter buy date",IF(TODAY()>=L6,"FUNDING UNLOCKED",L6-TODAY()&" days to go")) -> enter buy date
A7: AMKR | B7: Cash App | C7: Semi/AI | D7: 38.98181 | E7: 31.03 | F7: =IF(OR(D7="",E7=""),"",D7*E7) -> 1209.6056 | G7: 55.87 | H7: =IF(OR(D7="",G7=""),"",D7*G7) -> 2177.9137 | I7: =IF(OR(F7="",H7=""),"",H7-F7) -> 968.30816 | J7: =IF(OR(F7="",F7=0,I7=""),"",I7/F7) -> 0.80051563 | L7: =IF(K7="","",K7+366) | M7: =IF(K7="","enter buy date",IF(TODAY()>=L7,"FUNDING UNLOCKED",L7-TODAY()&" days to go")) -> enter buy date
A8: ASML | B8: Cash App | C8: Semi/AI | D8: 1.186848 | E8: 1015.39 | F8: =IF(OR(D8="",E8=""),"",D8*E8) -> 1205.1136 | G8: 1711.89 | H8: =IF(OR(D8="",G8=""),"",D8*G8) -> 2031.7532 | I8: =IF(OR(F8="",H8=""),"",H8-F8) -> 826.63963 | J8: =IF(OR(F8="",F8=0,I8=""),"",I8/F8) -> 0.68594333 | L8: =IF(K8="","",K8+366) | M8: =IF(K8="","enter buy date",IF(TODAY()>=L8,"FUNDING UNLOCKED",L8-TODAY()&" days to go")) -> enter buy date
A9: SOXX | B9: Cash App | C9: Semi/AI | D9: 3.3859551 | E9: 296.26 | F9: =IF(OR(D9="",E9=""),"",D9*E9) -> 1003.1231 | G9: 542.21 | H9: =IF(OR(D9="",G9=""),"",D9*G9) -> 1835.8987 | I9: =IF(OR(F9="",H9=""),"",H9-F9) -> 832.77565 | J9: =IF(OR(F9="",F9=0,I9=""),"",I9/F9) -> 0.83018295 | L9: =IF(K9="","",K9+366) | M9: =IF(K9="","enter buy date",IF(TODAY()>=L9,"FUNDING UNLOCKED",L9-TODAY()&" days to go")) -> enter buy date
A10: NBIS | B10: Cash App | C10: Semi/AI | D10: 9.0187672 | E10: 110.88 | F10: =IF(OR(D10="",E10=""),"",D10*E10) -> 1000.0009 | G10: 225.74 | H10: =IF(OR(D10="",G10=""),"",D10*G10) -> 2035.8965 | I10: =IF(OR(F10="",H10=""),"",H10-F10) -> 1035.8956 | J10: =IF(OR(F10="",F10=0,I10=""),"",I10/F10) -> 1.0358947 | L10: =IF(K10="","",K10+366) | M10: =IF(K10="","enter buy date",IF(TODAY()>=L10,"FUNDING UNLOCKED",L10-TODAY()&" days to go")) -> enter buy date
A11: AMD | B11: Cash App | C11: Semi/AI | D11: 1.6727076 | E11: 239.14 | F11: =IF(OR(D11="",E11=""),"",D11*E11) -> 400.01129 | G11: 518.58 | H11: =IF(OR(D11="",G11=""),"",D11*G11) -> 867.4327 | I11: =IF(OR(F11="",H11=""),"",H11-F11) -> 467.42141 | J11: =IF(OR(F11="",F11=0,I11=""),"",I11/F11) -> 1.1685205 | L11: =IF(K11="","",K11+366) | M11: =IF(K11="","enter buy date",IF(TODAY()>=L11,"FUNDING UNLOCKED",L11-TODAY()&" days to go")) -> enter buy date
A12: AVGO | B12: Cash App | C12: Semi/AI | D12: 2.8293049 | E12: 355.39 | F12: =IF(OR(D12="",E12=""),"",D12*E12) -> 1005.5067 | G12: 418.16 | H12: =IF(OR(D12="",G12=""),"",D12*G12) -> 1183.1021 | I12: =IF(OR(F12="",H12=""),"",H12-F12) -> 177.59547 | J12: =IF(OR(F12="",F12=0,I12=""),"",I12/F12) -> 0.17662287 | L12: =IF(K12="","",K12+366) | M12: =IF(K12="","enter buy date",IF(TODAY()>=L12,"FUNDING UNLOCKED",L12-TODAY()&" days to go")) -> enter buy date
A13: GOOGL | B13: Cash App | C13: AI-adjacent | D13: 3.8108817 | E13: 289.27 | F13: =IF(OR(D13="",E13=""),"",D13*E13) -> 1102.3737 | G13: 377.65 | H13: =IF(OR(D13="",G13=""),"",D13*G13) -> 1439.1795 | I13: =IF(OR(F13="",H13=""),"",H13-F13) -> 336.80572 | J13: =IF(OR(F13="",F13=0,I13=""),"",I13/F13) -> 0.30552771 | L13: =IF(K13="","",K13+366) | M13: =IF(K13="","enter buy date",IF(TODAY()>=L13,"FUNDING UNLOCKED",L13-TODAY()&" days to go")) -> enter buy date
A14: GLW | B14: Cash App | C14: AI-adjacent | D14: 3.776435 | E14: 132.4 | F14: =IF(OR(D14="",E14=""),"",D14*E14) -> 500 | G14: 159.89 | H14: =IF(OR(D14="",G14=""),"",D14*G14) -> 603.8142 | I14: =IF(OR(F14="",H14=""),"",H14-F14) -> 103.8142 | J14: =IF(OR(F14="",F14=0,I14=""),"",I14/F14) -> 0.2076284 | L14: =IF(K14="","",K14+366) | M14: =IF(K14="","enter buy date",IF(TODAY()>=L14,"FUNDING UNLOCKED",L14-TODAY()&" days to go")) -> enter buy date | O14: Optical fiber for AI data centers
A15: NVDA | B15: Robinhood | C15: Semi/AI | F15: =IF(OR(D15="",E15=""),"",D15*E15) | H15: =IF(OR(D15="",G15=""),"",D15*G15) | I15: =IF(OR(F15="",H15=""),"",H15-F15) | J15: =IF(OR(F15="",F15=0,I15=""),"",I15/F15) | L15: =IF(K15="","",K15+366) | M15: =IF(K15="","enter buy date",IF(TODAY()>=L15,"FUNDING UNLOCKED",L15-TODAY()&" days to go")) -> enter buy date | O15: From Stash ACATS — fill shares/cost when it lands
A16: TSLA | B16: Robinhood | C16: Other | F16: =IF(OR(D16="",E16=""),"",D16*E16) | H16: =IF(OR(D16="",G16=""),"",D16*G16) | I16: =IF(OR(F16="",H16=""),"",H16-F16) | J16: =IF(OR(F16="",F16=0,I16=""),"",I16/F16) | L16: =IF(K16="","",K16+366) | M16: =IF(K16="","enter buy date",IF(TODAY()>=L16,"FUNDING UNLOCKED",L16-TODAY()&" days to go")) -> enter buy date | O16: From Stash ACATS — fill shares/cost when it lands
A17: MSTR | B17: Cash App | C17: BTC | D17: 31.33598 | E17: 380.86 | F17: =IF(OR(D17="",E17=""),"",D17*E17) -> 11934.621 | G17: 97.65 | H17: =IF(OR(D17="",G17=""),"",D17*G17) -> 3059.9584 | I17: =IF(OR(F17="",H17=""),"",H17-F17) -> -8874.6628 | J17: =IF(OR(F17="",F17=0,I17=""),"",I17/F17) -> -0.74360657 | L17: =IF(K17="","",K17+366) | M17: =IF(K17="","enter buy date",IF(TODAY()>=L17,"FUNDING UNLOCKED",L17-TODAY()&" days to go")) -> enter buy date | O17: Conviction hold — separate bucket, not trim fuel
A19: TOTAL PARKED | F19: =SUM(F5:F17) -> 21821.17 | H19: =SUM(H5:H17) -> 22597.25 | I19: =SUM(I5:I17) -> 776.08028
A21: CONCENTRATION WATCH
A22: Semi/AI value | B22: =SUMIFS(H5:H17,C5:C17,"Semi/AI") -> 17494.298
A23: Semi/AI + AI-adjacent | B23: =B22+SUMIFS(H5:H17,C5:C17,"AI-adjacent") -> 19537.292
A24: Semi/AI % of pile | B24: =IF(H19=0,"",B22/H19) -> 0.77417819
A25: Semi/AI + adjacent % of pile | B25: =IF(H19=0,"",B23/H19) -> 0.86458714
A26: Target cap (edit) | B26: 0.5
A27: Status | B27: =IF(B24="","",IF(B24>B26,"OVER CAP — trim semis first","within cap")) -> OVER CAP — trim semis first
A29: Trim discipline: when a lot goes long-term, trim from Semi/AI first (double duty: fund the challenge account AND reduce concentration). Milestone skims from the challenge account buy VOO here.
